partypy/__init__.py
partypy/data/party.csv
partypy/datasets.py
partypy/plotting.py
partypy/simulate.py
partypy-0.4.0.dist-info/LICENSE
partypy-0.4.0.dist-info/WHEEL
partypy-0.4.0.dist-info/METADATA
partypy-0.4.0.dist-info/RECORD
