Metadata-Version: 2.1
Name: partypy
Version: 0.4.0
Summary: Simulate attendance at your party!
Home-page: https://github.com/TomasBeuzen/partypy
License: MIT
Author: Tomas Beuzen
Requires-Python: >=3.9,<4.0
Classifier: License :: OSI Approved :: MIT License
Classifier: Programming Language :: Python :: 3
Classifier: Programming Language :: Python :: 3.9
Classifier: Programming Language :: Python :: 3.10
Requires-Dist: altair (>=4.1.0,<5.0.0)
Requires-Dist: altair-viewer (>=0.3.0,<0.4.0)
Requires-Dist: numpy (>=1.21.1,<2.0.0)
Requires-Dist: pandas (>=1.3.1,<2.0.0)
Project-URL: Documentation, https://partypy.readthedocs.io/en/latest/
Project-URL: Repository, https://github.com/TomasBeuzen/partypy
